omuplugin_nyanya/__init__.py
omuplugin_nyanya/plugin.py
omuplugin_nyanya/version.py
omuplugin_nyanya-0.9.24.dist-info/METADATA
omuplugin_nyanya-0.9.24.dist-info/WHEEL
omuplugin_nyanya-0.9.24.dist-info/entry_points.txt
omuplugin_nyanya-0.9.24.dist-info/RECORD
