Metadata-Version: 2.4
Name: omuplugin_nyanya
Version: 0.9.24
Summary: にゃにゃにゃ？？
Author-email: am230 <111672334+am230@users.noreply.github.com>
Requires-Python: >=3.12
Requires-Dist: loguru>=0.7.2
Requires-Dist: omu-chat>=0.9.24
